odoo/addons/pos_pricelist_show_discount/README.rst
odoo/addons/pos_pricelist_show_discount/__init__.py
odoo/addons/pos_pricelist_show_discount/__manifest__.py
odoo/addons/pos_pricelist_show_discount/demo/res_users_demo.xml
odoo/addons/pos_pricelist_show_discount/i18n/it.po
odoo/addons/pos_pricelist_show_discount/i18n/pos_pricelist_show_discount.pot
odoo/addons/pos_pricelist_show_discount/models/__init__.py
odoo/addons/pos_pricelist_show_discount/models/pos_config.py
odoo/addons/pos_pricelist_show_discount/readme/CONFIGURE.rst
odoo/addons/pos_pricelist_show_discount/readme/CONTRIBUTORS.rst
odoo/addons/pos_pricelist_show_discount/readme/DESCRIPTION.rst
odoo/addons/pos_pricelist_show_discount/readme/USAGE.rst
odoo/addons/pos_pricelist_show_discount/static/description/icon.png
odoo/addons/pos_pricelist_show_discount/static/description/index.html
odoo/addons/pos_pricelist_show_discount/static/src/js/models.js
odoo/addons/pos_pricelist_show_discount/static/src/xml/Orderline.xml
odoo/addons/pos_pricelist_show_discount/static/tests/tours/pos_discount_ref_pricelist_tour.js
odoo/addons/pos_pricelist_show_discount/static/tests/tours/helpers/ProductScreenCustomTourMethods.js
odoo/addons/pos_pricelist_show_discount/templates/assets.xml
odoo/addons/pos_pricelist_show_discount/tests/__init__.py
odoo/addons/pos_pricelist_show_discount/tests/common.py
odoo/addons/pos_pricelist_show_discount/tests/test_pos_config_discount_pricelist.py
odoo/addons/pos_pricelist_show_discount/tests/test_pos_pricelist_show_discount.py
odoo/addons/pos_pricelist_show_discount/views/pos_config_view.xml
odoo14_addon_pos_pricelist_show_discount-14.0.1.0.5.dist-info/METADATA
odoo14_addon_pos_pricelist_show_discount-14.0.1.0.5.dist-info/WHEEL
odoo14_addon_pos_pricelist_show_discount-14.0.1.0.5.dist-info/top_level.txt
odoo14_addon_pos_pricelist_show_discount-14.0.1.0.5.dist-info/RECORD
